overzetten/__init__.py
overzetten/__main__.py
overzetten-0.1.0.dist-info/WHEEL
overzetten-0.1.0.dist-info/METADATA
overzetten-0.1.0.dist-info/RECORD
