Metadata-Version: 2.3
Name: overzetten
Version: 0.1.0
Summary: Instantly create pydantic schemas from your sqlalchemy models
Author: Matt LeMay
Author-email: Matt LeMay <mplemay@users.noreply.github.com>
Requires-Dist: pydantic>=2,<3
Requires-Dist: sqlalchemy>=2,<3
Requires-Python: >=3.11, <3.15
